dfval/__init__.py
dfval/dfval.py
dfval/dfcheck/__init__.py
dfval/dfcheck/dfcheck.py
dfval/dfclean/__init__.py
dfval/dfclean/dfclean.py
dfval/dfcompare/__init__.py
dfval/dfcompare/dfcompare.py
dfval-0.1.0.dist-info/LICENSE
dfval-0.1.0.dist-info/METADATA
dfval-0.1.0.dist-info/WHEEL
dfval-0.1.0.dist-info/top_level.txt
dfval-0.1.0.dist-info/RECORD
