Metadata-Version: 2.1
Name: dfval
Version: 0.1.0
Summary: A package for data validation with pandas dataframes
Home-page: https://github.com/ashendrickson/dfval
Author: Aaron Hendrickson
Author-email: ashendrickson@yahoo.com
License: Apache License 2.0
Platform: UNKNOWN
Requires-Dist: numpy
Requires-Dist: pandas
